MANIFEST.in
README.md
requirements.txt
setup.py
refunc_cli.egg-info/PKG-INFO
refunc_cli.egg-info/SOURCES.txt
refunc_cli.egg-info/dependency_links.txt
refunc_cli.egg-info/entry_points.txt
refunc_cli.egg-info/not-zip-safe
refunc_cli.egg-info/requires.txt
refunc_cli.egg-info/top_level.txt
rfctl/__init__.py
rfctl/__main__.py
rfctl/awslocal.py
rfctl/build.py
rfctl/common.py
rfctl/create.py
rfctl/create_url.py
rfctl/delete.py
rfctl/delete_url.py
rfctl/get.py
rfctl/get_url.py
rfctl/init.py
rfctl/init_source.py
rfctl/schema.py
rfctl/update_code.py
rfctl/update_config.py
rfctl/update_url.py
rfctl/client/__init__.py
rfctl/client/client.py