Metadata-Version: 2.1
Name: refunc-cli
Version: 1.3.12
Summary: refunc command line tools
Home-page: https://github.com/refunc/refunc-cli
Author: arvin
Author-email: arvintian8@gamil.com
License: MIT
Requires-Dist: aws_lambda_builders==1.30.0
Requires-Dist: jsonschema>=4.5.1
Requires-Dist: click>=8.1.3
Requires-Dist: awscli==1.37.5
Requires-Dist: boto3==1.36.5
Requires-Dist: pretty-logging>=1.0.3
